README.md
setup.py
xueqiudanjuan/__init__.py
xueqiudanjuan/engine.py
xueqiudanjuan/hello.py
xueqiudanjuan/stocks.py
xueqiudanjuan.egg-info/PKG-INFO
xueqiudanjuan.egg-info/SOURCES.txt
xueqiudanjuan.egg-info/dependency_links.txt
xueqiudanjuan.egg-info/top_level.txt