Metadata-Version: 2.1
Name: xueqiudanjuan
Version: 0.0.11
Summary: This is a package provided by BugMakerH.
Home-page: https://github.com/BugMakerH/xueqiudanjuan.git
Author: BugMakerH
Author-email: BugMakerH@gmail.com
License: UNKNOWN
Platform: UNKNOWN
Classifier: Programming Language :: Python :: 3
Classifier: License :: OSI Approved :: Apache Software License
Classifier: Operating System :: OS Independent
